LICENSE
MANIFEST.in
README.rst
requirements.txt
setup.py
supergauge/__init__.py
supergauge/consts.py
supergauge/eventlistener.py
supergauge/gauge.py
supergauge/unit.py
supergauge/utils.py
supergauge.egg-info/PKG-INFO
supergauge.egg-info/SOURCES.txt
supergauge.egg-info/dependency_links.txt
supergauge.egg-info/entry_points.txt
supergauge.egg-info/not-zip-safe
supergauge.egg-info/pbr.json
supergauge.egg-info/requires.txt
supergauge.egg-info/top_level.txt
supergauge/plugins/__init__.py
supergauge/plugins/ali_cms.py
supergauge/plugins/baidu_bcm.py
supergauge/plugins/echo.py