Metadata-Version: 1.0
Name: supergauge
Version: 0.0.2
Summary: supervisor process gauge eventlistener
Home-page: https://github.com/skylothar/super-gauge
Author: SkyLothar
Author-email: allothar@gmail.com
License: UNKNOWN
Platform: UNKNOWN
